sm_client_libs/__init__.py
sm_client_libs/exception.py
sm_client_libs/schemes/__init__.py
sm_client_libs/schemes/secrets.py
sm_client_libs/schemes/servers.py
sm_client_libs/schemes/systems.py
sm_client_libs/service.py
settings_manager_client_libs-0.1.1.dist-info/METADATA
settings_manager_client_libs-0.1.1.dist-info/WHEEL
settings_manager_client_libs-0.1.1.dist-info/RECORD
