Metadata-Version: 2.1
Name: settings-manager-client-libs
Version: 0.1.1
Summary: 
Author: DKrivov
Author-email: 55reigen55@mail.ru
Requires-Python: ==3.9.13
Classifier: Programming Language :: Python :: 3
Requires-Dist: httpx (>=0.25.2,<0.26.0)
Requires-Dist: pydantic (>=2.5.2,<3.0.0)
